timvt/__init__.py
timvt/db.py
timvt/dependencies.py
timvt/errors.py
timvt/factory.py
timvt/layer.py
timvt/main.py
timvt/settings.py
timvt/models/OGC.py
timvt/models/__init__.py
timvt/models/mapbox.py
timvt/resources/__init__.py
timvt/resources/enums.py
timvt/templates/index.html
timvt/templates/viewer.html
timvt-0.7.0.dist-info/LICENSE
timvt-0.7.0.dist-info/WHEEL
timvt-0.7.0.dist-info/METADATA
timvt-0.7.0.dist-info/RECORD
