Metadata-Version: 2.1
Name: timvt
Version: 0.7.0
Summary: A lightweight PostGIS based dynamic vector tile server.
Keywords: FastAPI,MVT,POSTGIS
Author-email: Vincent Sarago <vincent@developmentseed.com>
Requires-Python: >=3.7
Classifier: Intended Audience :: Information Technology
Classifier: Intended Audience :: Science/Research
Classifier: License :: OSI Approved :: BSD License
Classifier: Programming Language :: Python :: 3.7
Classifier: Programming Language :: Python :: 3.8
Classifier: Programming Language :: Python :: 3.9
Classifier: Topic :: Scientific/Engineering :: GIS
Requires-Dist: asyncpg>=0.23.0
Requires-Dist: buildpg>=0.3
Requires-Dist: fastapi>=0.73
Requires-Dist: jinja2>=2.11.2,<4.0.0
Requires-Dist: morecantile>=3.1,<4.0
Requires-Dist: starlette-cramjam>=0.3,<0.4
Requires-Dist: importlib_resources>=1.1.0; python_version < '3.9'
Requires-Dist: pre-commit ; extra == "dev"
Requires-Dist: nbconvert ; extra == "docs"
Requires-Dist: mkdocs ; extra == "docs"
Requires-Dist: mkdocs-material ; extra == "docs"
Requires-Dist: mkdocs-jupyter ; extra == "docs"
Requires-Dist: pygments ; extra == "docs"
Requires-Dist: pdocs ; extra == "docs"
Requires-Dist: uvicorn[standard]>=0.12.0,<0.16.0 ; extra == "server"
Requires-Dist: pytest ; extra == "test"
Requires-Dist: pytest-cov ; extra == "test"
Requires-Dist: pytest-asyncio ; extra == "test"
Requires-Dist: requests ; extra == "test"
Requires-Dist: psycopg2 ; extra == "test"
Requires-Dist: pytest-pgsql ; extra == "test"
Requires-Dist: mapbox-vector-tile ; extra == "test"
Requires-Dist: protobuf>=3.0,<4.0 ; extra == "test"
Requires-Dist: numpy ; extra == "test"
Project-URL: Documentation, https://developmentseed.org/timvt/
Project-URL: Source, https://github.com/developmentseed/timvt
Provides-Extra: dev
Provides-Extra: docs
Provides-Extra: server
Provides-Extra: test
